.gitignore
LICENSE
README.md
README.rst
setup.py
test.txt
tox.ini
nutrinews/__init__.py
nutrinews/nutrinews.py
nutrinews.egg-info/PKG-INFO
nutrinews.egg-info/SOURCES.txt
nutrinews.egg-info/dependency_links.txt
nutrinews.egg-info/entry_points.txt
nutrinews.egg-info/requires.txt
nutrinews.egg-info/top_level.txt
tests/test_sample.py