Metadata-Version: 2.1
Name: nutrinews
Version: 0.1.0
Summary: Make news more nutritious by removing bias.
Home-page: https://github.com/devbisme/nutrinews
Author: Dave Vandenbout
Author-email: devb@xess.com
License: MIT
Classifier: Development Status :: 2 - Pre-Alpha
Classifier: License :: OSI Approved :: MIT License
Classifier: Programming Language :: Python
Classifier: Programming Language :: Python :: 3
License-File: LICENSE
